one_electron_matrices/__init__.py
one_electron_matrices/oem_rep.py
one_electron_matrices-0.0.1.dist-info/METADATA
one_electron_matrices-0.0.1.dist-info/WHEEL
one_electron_matrices-0.0.1.dist-info/licenses/LICENSE
one_electron_matrices-0.0.1.dist-info/RECORD
