Metadata-Version: 2.4
Name: one_electron_matrices
Version: 0.0.1
Summary: Code responsible for generating the one-electron integrals.
Project-URL: Homepage, https://github.com/grynova-ccc/quantum_periodic_representations
Author-email: Stiv Llenga <stivllenga@gmail.com>
License-File: LICENSE
Classifier: License :: OSI Approved :: MIT License
Classifier: Operating System :: OS Independent
Classifier: Programming Language :: Python :: 3
Requires-Python: >=3.7
